axpg/__init__.py
axpg/__main__.py
axpg/core.py
axpg/menu.py
axpg-0.1.3.dist-info/METADATA
axpg-0.1.3.dist-info/WHEEL
axpg-0.1.3.dist-info/RECORD
