Metadata-Version: 2.1
Name: axpg
Version: 0.1.3
Summary: 
Author: axdjuraev
Author-email: axdjuraev@gmail.com
Requires-Python: >=3.10,<4.0
Classifier: Programming Language :: Python :: 3
Classifier: Programming Language :: Python :: 3.10
Classifier: Programming Language :: Python :: 3.11
Requires-Dist: colorama (>=0.4.6,<0.5.0)
